qustop
research
