Metadata-Version: 2.1
Name: qustop
Version: 0.0.3
Summary: Python toolkit for studying quantum state optimization problems
Home-page: https://github.com/vprusso/toqito
Author: Vincent Russo
Author-email: vincentrusso1@gmail.com
License: UNKNOWN
Platform: UNKNOWN
Classifier: Development Status :: 5 - Production/Stable
Classifier: Intended Audience :: Science/Research
Classifier: Topic :: Scientific/Engineering :: Physics
Classifier: Programming Language :: Python :: 3
Classifier: License :: OSI Approved :: BSD License
Classifier: Operating System :: OS Independent
Requires-Python: >=3.9
